rbi_ml/__init__.py
rbi_ml/lightning/__init__.py
rbi_ml/lightning/callbacks_base.py
rbi_ml/lightning/datasets_base.py
rbi_ml/lightning/loggers_base.py
rbi_ml/lightning/multitask.py
rbi_ml/lightning/tft_inventory_forecast.py
rbi_ml/lightning/txt.py
rbi_ml/lightning/wide_and_deep.py
rbi_ml/models/__init__.py
rbi_ml/models/mmoe.py
rbi_ml/models/multitask.py
rbi_ml/models/txt.py
rbi_ml/models/wide_and_deep.py
rbi_ml/offers/__init__.py
rbi_ml/offers/adhoc_offers.py
rbi_ml/offers/app_mxnet_inference.py
rbi_ml/offers/app_txt_inference.py
rbi_ml/offers/models.py
rbi_ml/offers/offers.py
rbi_ml/offers/segment_rules.py
rbi_ml/offers/torch_layers.py
rbi_ml/offers/transformation.py
rbi_ml/offers/utils.py
rbi_ml/offers/utils_daily.py
rbi_ml/offers/utils_mxnet.py
rbi_ml/offers/utils_ncf.py
rbi_ml/offers/utils_offer2vec.py
rbi_ml/offers/utils_offer_encoder.py
rbi_ml/offers/utils_weekly.py
rbi_ml/utils/__init__.py
rbi_ml/utils/utils.py
rbi_ml-0.0.34.dist-info/LICENSE
rbi_ml-0.0.34.dist-info/METADATA
rbi_ml-0.0.34.dist-info/WHEEL
rbi_ml-0.0.34.dist-info/top_level.txt
rbi_ml-0.0.34.dist-info/RECORD
