Metadata-Version: 2.1
Name: rbi_ml
Version: 0.0.34
Summary: rbi ml packages
Home-page: https://gitlab.com/rbibigdata/mldp/rbi-ml/-/tree/rbi_ml_package
Author: ctang
Author-email: ctang@rbi.com
License: UNKNOWN
Platform: UNKNOWN
Classifier: Programming Language :: Python :: 3
Classifier: License :: OSI Approved :: MIT License
Classifier: Operating System :: OS Independent
Requires-Python: >=3.5
License-File: LICENSE
